{"Hitters": {"Tyrone Taylor": [["Tyrone Taylor", "CF", "B/T: R/R", "6' 0\" 185", "Age: 25", "Draft: 2012 (Rd: 2, #92, Milwaukee Brewers )  - Torrance HS (CA)", "Torrance, CA USA", "MLB Pipeline Rank:", "MIL", ": No. 26", "Player Apps", "Pitch Highlighter", "Player Similarity", "Shifts", "Zone Swing Profile", [], "Rookie"], {"Seasons": 1, "G": 2, "PA": 2, "AB": 1.0, "R": 0.0, "H": 1.0, "2B": 0.0, "3B": 0.0, "HR": 0.0, "RBI": 1.0, "BB": 0.0, "SO": 0.0, "SB": 0.0, "CS": 0.0, "HBP": 1.0, "AVG": 1.0, "OBP": 1.0, "SLG": 1.0, "OPS": 2, "TB": 1.0, "LOB": 0.0, "SAC": 0.0, "SF": 0.0, "BABIP": 1.0, "XBH": 0.0, "GIDP": 0.0, "GIDPO": 0.0, "NP": 6, "P/PA": 3, "K/PA": 0.0, "HR/PA": 0.0, "BB/K": NaN, "ISO": 0.0, "ROE": 0.0, "WO": 0.0, "Pitches": 6, "Batted Balls": 1.0, "Barrels": 0.0, "Barrel %": 0.0, "Exit Velocity": 99.1, "Launch Angle": 3.2, "XBA": 0.524, "XSLG": 0.593, "WOBA": 0.798, "XWOBA": 0.602, "XWOBACON": 0.483, "Hard Hit %": 100, "K %": 0.0, "BB %": 0.0, "Days injured": 35, "Number of injuries": 5, "Zone %": 50, "Zone Swing %": 33.3, "Zone Contact %": 100, "Chase %": 33.3, "Chase Contact %": 100, "Edge %": 16.7, "1st Pitch Swing %": 0.0, "Swing %": 33.3, "Whiff %": 0.0, "Meatball %": 0.0, "Meatball Swing %": NaN}], "Tyler Austin": [["Tyler Austin", "1B", "B/T: R/R", "6' 2\" 220", "Age: 28", "Draft: 2010 (Rd: 13, #415, New York Yankees )  - Heritage HS", "Conyers, GA USA", "Player Apps", "Pitch Highlighter", "Player Similarity", "Shifts", "Zone Swing Profile", ["1B", "LF", "RF", "OF"], "Young guy"], {"Seasons": 4, "G": 200, "PA": 567, "AB": 506, "R": 75, "H": 112, "2B": 18, "3B": 1.0, "HR": 33, "RBI": 91, "BB": 53, "SO": 210, "SB": 4, "CS": 2, "HBP": 2, "AVG": 0.221, "OBP": 0.295, "SLG": 0.457, "OPS": 0.751, "TB": 231, "LOB": 222, "SAC": 0.0, "SF": 6, "BABIP": 0.294, "XBH": 52, "GIDP": 6, "GIDPO": 67, "NP": 2415, "P/PA": 4.26, "K/PA": 0.37, "HR/PA": 0.058, "BB/K": 0.252, "ISO": 0.235, "ROE": 0.235, "WO": 1.0, "Pitches": 2415, "Batted Balls": 302, "Barrels": 49, "Barrel %": 16.2, "Exit Velocity": 89.6, "Launch Angle": 14.3, "XBA": 0.22, "XSLG": 0.465, "WOBA": 0.319, "XWOBA": 0.325, "XWOBACON": 0.486, "Hard Hit %": 42.7, "K %": 37, "BB %": 9.3, "Days injured": 116, "Number of injuries": 9, "Zone %": 47.1, "Zone Swing %": 69.4, "Zone Contact %": 72, "Chase %": 28, "Chase Contact %": 37.5, "Edge %": 42.7, "1st Pitch Swing %": 27.7, "Swing %": 47.5, "Whiff %": 38.8, "Meatball %": 6.6, "Meatball Swing %": 81, "% Rank": 51.0}], "Jacob Nottingham": [["Jacob Nottingham", "C", "B/T: R/R", "6' 2\" 230", "Age: 24", "Draft: 2013 (Rd: 6, #167, Houston Astros )  - Redlands (CA) HS", "Redlands, CA USA", "Player Apps", "Pitch Highlighter", "Player Similarity", "Shifts", "Zone Swing Profile", ["C", "1B"], "Young guy"], {"Seasons": 2, "G": 15, "PA": 29, "AB": 25, "R": 3, "H": 6, "2B": 1.0, "3B": 0.0, "HR": 1.0, "RBI": 4, "BB": 4, "SO": 10, "SB": 0.0, "CS": 0.0, "HBP": 0.0, "AVG": 0.24, "OBP": 0.345, "SLG": 0.4, "OPS": 0.745, "TB": 10, "LOB": 11, "SAC": 0.0, "SF": 0.0, "BABIP": 0.357, "XBH": 2, "GIDP": 0.0, "GIDPO": 2, "NP": 136, "P/PA": 4.69, "K/PA": 0.345, "HR/PA": 0.034, "BB/K": 0.4, "ISO": 0.16, "ROE": 0.16, "WO": 0.0, "Pitches": 136, "Batted Balls": 15, "Barrels": 0.0, "Barrel %": 0.0, "Exit Velocity": 88.5, "Launch Angle": 15.4, "XBA": 0.165, "XSLG": 0.207, "WOBA": 0.328, "XWOBA": 0.235, "XWOBACON": 0.271, "Hard Hit %": 33.3, "K %": 34.5, "BB %": 13.8, "Days injured": 14, "Number of injuries": 2, "Zone %": 50, "Zone Swing %": 58.8, "Zone Contact %": 72.5, "Chase %": 22.1, "Chase Contact %": 46.7, "Edge %": 40.4, "1st Pitch Swing %": 13.8, "Swing %": 40.4, "Whiff %": 34.5, "Meatball %": 9.6, "Meatball Swing %": 92.3, "% Rank": 57.5}], "Christian Yelich": [["Christian Yelich", "RF", "B/T: L/R", "6' 3\" 195", "Age: 27", "Draft: 2010 (Rd: 1, #23, Florida Marlins )  - Westlake HS", "Thousand Oaks, CA USA", "Popularity:", "\u2193 -38%", "Player Apps", "Pitch Highlighter", "Player Similarity", "Shifts", "Zone Swing Profile", ["LF", "CF", "RF", "OF"], "Vet"], {"Seasons": 7, "G": 920, "PA": 4043, "AB": 3541, "R": 587, "H": 1067, "2B": 209, "3B": 24, "HR": 139, "RBI": 500, "BB": 448, "SO": 832, "SB": 124, "CS": 24, "HBP": 31, "AVG": 0.301, "OBP": 0.383, "SLG": 0.492, "OPS": 0.874, "TB": 1741, "LOB": 1323, "SAC": 3, "SF": 19, "BABIP": 0.358, "XBH": 372, "GIDP": 81, "GIDPO": 562, "NP": 16523, "P/PA": 4.09, "K/PA": 0.206, "HR/PA": 0.034, "BB/K": 0.538, "ISO": 0.19, "ROE": 0.19, "WO": 7, "FPCT %": 0.9890000000000001, "Pitches": 12539, "Batted Balls": 2106, "Barrels": 210, "Barrel %": 10, "Exit Velocity": 91.9, "Launch Angle": 4.5, "XBA": 0.309, "XSLG": 0.517, "WOBA": 0.385, "XWOBA": 0.391, "XWOBACON": 0.457, "Hard Hit %": 48.2, "K %": 20.2, "BB %": 11.2, "Days injured": 62, "Number of injuries": 5, "Zone %": 45.9, "Zone Swing %": 64.9, "Zone Contact %": 85.6, "Chase %": 24.1, "Chase Contact %": 54.3, "Edge %": 42.3, "1st Pitch Swing %": 23.2, "Swing %": 42.8, "Whiff %": 24, "Meatball %": 6.3, "Meatball Swing %": 77.9, "% Rank": 88.7}], "Keston Hiura": [["Keston Hiura", "2B", "B/T: R/R", "5' 11\" 190", "Age: 23", "Draft: 2017 (Rd: 1, #9, Milwaukee Brewers )  - UC Irvine", "Valencia, CA USA", "Player Apps", "Pitch Highlighter", "Player Similarity", "Shifts", "Zone Swing Profile", [], "Rookie"], {"Seasons": 1, "G": 70, "PA": 295, "AB": 266, "R": 44, "H": 80, "2B": 20, "3B": 2, "HR": 16, "RBI": 43, "BB": 23, "SO": 89, "SB": 9, "CS": 3, "HBP": 6, "AVG": 0.301, "OBP": 0.369, "SLG": 0.571, "OPS": 0.941, "TB": 152, "LOB": 122, "SAC": 0.0, "SF": 0.0, "BABIP": 0.398, "XBH": 38, "GIDP": 4, "GIDPO": 31, "NP": 1167, "P/PA": 3.96, "K/PA": 0.302, "HR/PA": 0.054, "BB/K": 0.258, "ISO": 0.271, "ROE": 0.271, "WO": 1.0, "FPCT %": 0.9570000000000001, "Pitches": 1167, "Batted Balls": 177, "Barrels": 25, "Barrel %": 14.1, "Exit Velocity": 91.5, "Launch Angle": 16.6, "XBA": 0.263, "XSLG": 0.51, "WOBA": 0.394, "XWOBA": 0.362, "XWOBACON": 0.49, "Hard Hit %": 48.6, "K %": 30.2, "BB %": 7.8, "Days injured": 17, "Number of injuries": 2, "Zone %": 48.2, "Zone Swing %": 72.8, "Zone Contact %": 74, "Chase %": 31.2, "Chase Contact %": 41.9, "Edge %": 42.7, "1st Pitch Swing %": 32.9, "Swing %": 51.4, "Whiff %": 36.2, "Meatball %": 6.4, "Meatball Swing %": 75.7, "% Rank": 55.4}], "Ryan Braun": [["Ryan Braun", "LF", "B/T: R/R", "6' 2\" 205", "Age: 35", "Draft: 2005 (Rd: 1, #5, Milwaukee Brewers )  - Miami (FL)", "Mission Hills, CA USA", "Popularity:", "\u2193 -45%", "Player Apps", "Pitch Highlighter", "Player Similarity", "Shifts", "Zone Swing Profile", ["1B", "3B", "LF", "CF", "RF", "OF"], "Old timer"], {"Seasons": 13, "G": 1715, "PA": 7159, "AB": 6457, "R": 1056, "H": 1920, "2B": 397, "3B": 48, "HR": 340, "RBI": 1113, "BB": 576, "SO": 1327, "SB": 214, "CS": 60, "HBP": 74, "AVG": 0.297, "OBP": 0.359, "SLG": 0.532, "OPS": 0.891, "TB": 3433, "LOB": 2622, "SAC": 0.0, "SF": 43, "BABIP": 0.327, "XBH": 785, "GIDP": 173, "GIDPO": 1120, "NP": 26571, "P/PA": 3.71, "K/PA": 0.185, "HR/PA": 0.047, "BB/K": 0.434, "ISO": 0.234, "ROE": 0.234, "WO": 11, "FPCT %": 0.9890000000000001, "Pitches": 9089, "Batted Balls": 1771, "Barrels": 169, "Barrel %": 9.5, "Exit Velocity": 90.9, "Launch Angle": 6.3, "XBA": 0.286, "XSLG": 0.49, "WOBA": 0.355, "XWOBA": 0.361, "XWOBACON": 0.419, "Hard Hit %": 44.2, "K %": 19, "BB %": 8.2, "Days injured": 70, "Number of injuries": 6, "Zone %": 45.1, "Zone Swing %": 71.2, "Zone Contact %": 86.3, "Chase %": 34.5, "Chase Contact %": 62.4, "Edge %": 41.6, "1st Pitch Swing %": 38.9, "Swing %": 51.1, "Whiff %": 22.6, "Meatball %": 6.2, "Meatball Swing %": 79.3, "% Rank": 45.5}], "Mike Moustakas": [["Mike Moustakas", "2B", "B/T: L/R", "6' 0\" 225", "Age: 31", "Draft: 2007 (Rd: 1, #2, Kansas City Royals )  - Chatsworth (CA) HS", "Los Angeles, CA USA", "Player Apps", "Pitch Highlighter", "Player Similarity", "Shifts", "Zone Swing Profile", ["1B", "2B", "3B"], "Vet"], {"Seasons": 9, "G": 1115, "PA": 4479, "AB": 4084, "R": 481, "H": 1033, "2B": 224, "3B": 6, "HR": 180, "RBI": 555, "BB": 309, "SO": 705, "SB": 18, "CS": 10, "HBP": 45, "AVG": 0.253, "OBP": 0.31, "SLG": 0.443, "OPS": 0.753, "TB": 1809, "LOB": 1736, "SAC": 8, "SF": 33, "BABIP": 0.264, "XBH": 410, "GIDP": 95, "GIDPO": 695, "NP": 17344, "P/PA": 3.87, "K/PA": 0.157, "HR/PA": 0.04, "BB/K": 0.438, "ISO": 0.19, "ROE": 0.19, "WO": 3, "FPCT %": 0.993, "Pitches": 9523, "Batted Balls": 1903, "Barrels": 164, "Barrel %": 8.6, "Exit Velocity": 88.8, "Launch Angle": 17, "XBA": 0.264, "XSLG": 0.474, "WOBA": 0.347, "XWOBA": 0.343, "XWOBACON": 0.375, "Hard Hit %": 37.7, "K %": 15, "BB %": 7.3, "Days injured": 75, "Number of injuries": 2, "Zone %": 46.3, "Zone Swing %": 70.5, "Zone Contact %": 86.8, "Chase %": 33.5, "Chase Contact %": 65.5, "Edge %": 43.3, "1st Pitch Swing %": 29.1, "Swing %": 50.7, "Whiff %": 20.8, "Meatball %": 6.7, "Meatball Swing %": 79.8, "% Rank": 26.3}], "Trent Grisham": [["Trent Grisham", "RF", "B/T: L/L", "6' 0\" 205", "Age: 22", "Draft: 2015 (Rd: 1, #15, Milwaukee Brewers )  - Richland (TX) HS", "Fort Worth, TX USA", "MLB Pipeline Rank:", "MIL", ": No. 6", "Player Apps", "Pitch Highlighter", "Player Similarity", "Shifts", "Zone Swing Profile", ["LF", "CF", "RF", "OF"], "Rookie"], {"Seasons": 1, "G": 34, "PA": 116, "AB": 104, "R": 15, "H": 27, "2B": 5, "3B": 1.0, "HR": 5, "RBI": 14, "BB": 8, "SO": 31, "SB": 0.0, "CS": 0.0, "HBP": 2, "AVG": 0.26, "OBP": 0.319, "SLG": 0.471, "OPS": 0.79, "TB": 49, "LOB": 39, "SAC": 0.0, "SF": 2, "BABIP": 0.314, "XBH": 11, "GIDP": 2, "GIDPO": 16, "NP": 482, "P/PA": 4.16, "K/PA": 0.267, "HR/PA": 0.043, "BB/K": 0.258, "ISO": 0.212, "ROE": 0.212, "WO": 0.0, "FPCT %": 1.0, "Pitches": 482, "Batted Balls": 75, "Barrels": 5, "Barrel %": 6.7, "Exit Velocity": 89.3, "Launch Angle": 18.2, "XBA": 0.252, "XSLG": 0.416, "WOBA": 0.33, "XWOBA": 0.315, "XWOBACON": 0.399, "Hard Hit %": 41.3, "K %": 27.4, "BB %": 6.8, "Days injured": 21, "Number of injuries": 3, "Zone %": 54.1, "Zone Swing %": 56.7, "Zone Contact %": 83.1, "Chase %": 21.3, "Chase Contact %": 59.6, "Edge %": 40.9, "1st Pitch Swing %": 16.2, "Swing %": 40.5, "Whiff %": 22.6, "Meatball %": 8.5, "Meatball Swing %": 75.6, "% Rank": 94.5}], "Ben Gamel": [["Ben Gamel", "LF", "B/T: L/L", "5' 11\" 185", "Age: 27", "Draft: 2010 (Rd: 10, #325, New York Yankees )  - Bishop Kenny HS", "Neptune Beach, FL USA", "Player Apps", "Pitch Highlighter", "Player Similarity", "Shifts", "Zone Swing Profile", ["1B", "LF", "CF", "RF", "OF"], "Young guy"], {"Seasons": 4, "G": 387, "PA": 1215, "AB": 1092, "R": 156, "H": 290, "2B": 58, "3B": 9, "HR": 20, "RBI": 114, "BB": 105, "SO": 290, "SB": 13, "CS": 6, "HBP": 8, "AVG": 0.266, "OBP": 0.333, "SLG": 0.39, "OPS": 0.723, "TB": 426, "LOB": 391, "SAC": 4, "SF": 6, "BABIP": 0.343, "XBH": 87, "GIDP": 13, "GIDPO": 145, "NP": 4934, "P/PA": 4.06, "K/PA": 0.239, "HR/PA": 0.016, "BB/K": 0.362, "ISO": 0.125, "ROE": 0.125, "WO": 1.0, "FPCT %": 0.983, "Pitches": 4934, "Batted Balls": 812, "Barrels": 31, "Barrel %": 3.8, "Exit Velocity": 87.5, "Launch Angle": 9.2, "XBA": 0.25, "XSLG": 0.366, "WOBA": 0.314, "XWOBA": 0.304, "XWOBACON": 0.361, "Hard Hit %": 33.3, "K %": 23.9, "BB %": 8.6, "Days injured": 31, "Number of injuries": 4, "Zone %": 49.7, "Zone Swing %": 60.9, "Zone Contact %": 86.6, "Chase %": 24.4, "Chase Contact %": 58.9, "Edge %": 42.4, "1st Pitch Swing %": 13.4, "Swing %": 42.5, "Whiff %": 21.5, "Meatball %": 7.3, "Meatball Swing %": 70.9, "% Rank": 75.5}], "Yasmani Grandal": [["Yasmani Grandal", "C", "B/T: S/R", "6' 1\" 235", "Age: 30", "Draft: 2010 (Rd: 1, #12, Cincinnati Reds )  - Miami", "Havana,  Cuba", "Popularity:", "\u2193 -57%", "Player Apps", "Pitch Highlighter", "Player Similarity", "Shifts", "Zone Swing Profile", ["C", "1B"], "Vet"], {"Seasons": 8, "G": 863, "PA": 3226, "AB": 2741, "R": 363, "H": 664, "2B": 133, "3B": 7, "HR": 139, "RBI": 410, "BB": 443, "SO": 755, "SB": 11, "CS": 7, "HBP": 16, "AVG": 0.242, "OBP": 0.348, "SLG": 0.448, "OPS": 0.796, "TB": 1228, "LOB": 1187, "SAC": 2, "SF": 24, "BABIP": 0.281, "XBH": 279, "GIDP": 79, "GIDPO": 395, "NP": 13507, "P/PA": 4.19, "K/PA": 0.234, "HR/PA": 0.043, "BB/K": 0.587, "ISO": 0.206, "ROE": 0.206, "WO": 4, "Pitches": 10315, "Batted Balls": 1518, "Barrels": 159, "Barrel %": 10.5, "Exit Velocity": 89.6, "Launch Angle": 12.6, "XBA": 0.228, "XSLG": 0.44, "WOBA": 0.347, "XWOBA": 0.339, "XWOBACON": 0.39, "Hard Hit %": 41.4, "K %": 23.8, "BB %": 13.7, "Days injured": 111, "Number of injuries": 6, "Zone %": 46.9, "Zone Swing %": 60.1, "Zone Contact %": 81.2, "Chase %": 22.8, "Chase Contact %": 55.7, "Edge %": 43.9, "1st Pitch Swing %": 24, "Swing %": 40.3, "Whiff %": 26.6, "Meatball %": 6.3, "Meatball Swing %": 72.3, "% Rank": 9.4}], "Lorenzo Cain": [["Lorenzo Cain", "CF", "B/T: R/R", "6' 2\" 205", "Age: 33", "Draft: 2004 (Rd: 17, #496, Milwaukee Brewers )  - Madison County HS (FL)", "Valdosta, GA USA", "Popularity:", "\u2193 -18%", "Player Apps", "Pitch Highlighter", "Player Similarity", "Shifts", "Zone Swing Profile", ["LF", "CF", "RF", "OF"], "Vet"], {"Seasons": 10, "G": 1029, "PA": 4240, "AB": 3843, "R": 558, "H": 1105, "2B": 203, "3B": 24, "HR": 75, "RBI": 401, "BB": 322, "SO": 758, "SB": 173, "CS": 39, "HBP": 45, "AVG": 0.288, "OBP": 0.347, "SLG": 0.411, "OPS": 0.759, "TB": 1581, "LOB": 1427, "SAC": 0.0, "SF": 30, "BABIP": 0.339, "XBH": 302, "GIDP": 98, "GIDPO": 555, "NP": 16656, "P/PA": 3.93, "K/PA": 0.179, "HR/PA": 0.018, "BB/K": 0.425, "ISO": 0.124, "ROE": 0.124, "WO": 6, "FPCT %": 0.985, "Pitches": 11313, "Batted Balls": 2126, "Barrels": 88, "Barrel %": 4.1, "Exit Velocity": 89.3, "Launch Angle": 8, "XBA": 0.298, "XSLG": 0.427, "WOBA": 0.338, "XWOBA": 0.347, "XWOBACON": 0.381, "Hard Hit %": 37.8, "K %": 16.4, "BB %": 8.4, "Days injured": 129, "Number of injuries": 7, "Zone %": 49, "Zone Swing %": 67.1, "Zone Contact %": 88.4, "Chase %": 26.6, "Chase Contact %": 61.2, "Edge %": 42.5, "1st Pitch Swing %": 26.1, "Swing %": 46.5, "Whiff %": 19.6, "Meatball %": 7.2, "Meatball Swing %": 74.8, "% Rank": 72.1}], "Eric Thames": [["Eric Thames", "1B", "B/T: L/R", "6' 0\" 210", "Age: 32", "Draft: 2008 (Rd: 7, #219, Toronto Blue Jays )  - Pepperdine", "Santa Clara, CA USA", "Player Apps", "Pitch Highlighter", "Player Similarity", "Shifts", "Zone Swing Profile", ["1B", "LF", "RF", "OF"], "Young guy"], {"Seasons": 5, "G": 548, "PA": 1915, "AB": 1694, "R": 266, "H": 415, "2B": 92, "3B": 17, "HR": 89, "RBI": 217, "BB": 190, "SO": 559, "SB": 17, "CS": 6, "HBP": 22, "AVG": 0.245, "OBP": 0.328, "SLG": 0.477, "OPS": 0.805, "TB": 808, "LOB": 706, "SAC": 2, "SF": 7, "BABIP": 0.31, "XBH": 198, "GIDP": 23, "GIDPO": 214, "NP": 7702, "P/PA": 4.02, "K/PA": 0.292, "HR/PA": 0.046, "BB/K": 0.34, "ISO": 0.232, "ROE": 0.232, "WO": 4, "Pitches": 5136, "Batted Balls": 679, "Barrels": 81, "Barrel %": 11.9, "Exit Velocity": 89.6, "Launch Angle": 16.2, "XBA": 0.223, "XSLG": 0.442, "WOBA": 0.358, "XWOBA": 0.333, "XWOBACON": 0.438, "Hard Hit %": 41, "K %": 31.1, "BB %": 12.4, "Days injured": 41, "Number of injuries": 5, "Zone %": 45.6, "Zone Swing %": 68.4, "Zone Contact %": 77.6, "Chase %": 26.3, "Chase Contact %": 46, "Edge %": 42.9, "1st Pitch Swing %": 26.8, "Swing %": 45.5, "Whiff %": 32.4, "Meatball %": 6.2, "Meatball Swing %": 80.8, "% Rank": 47.6}], "Cory Spangenberg": [["Cory Spangenberg", "3B", "B/T: L/R", "6' 0\" 195", "Age: 28", "Draft: 2011 (Rd: 1, #10, San Diego Padres )  - Indain River CC", "Clarks Summit, PA USA", "Player Apps", "Pitch Highlighter", "Player Similarity", "Shifts", "Zone Swing Profile", ["P", "2B", "3B", "SS", "LF", "CF", "RF", "OF"], "Young guy"], {"Seasons": 6, "G": 404, "PA": 1338, "AB": 1212, "R": 149, "H": 312, "2B": 49, "3B": 14, "HR": 28, "RBI": 113, "BB": 95, "SO": 359, "SB": 32, "CS": 10, "HBP": 10, "AVG": 0.257, "OBP": 0.316, "SLG": 0.39, "OPS": 0.706, "TB": 473, "LOB": 453, "SAC": 16, "SF": 4, "BABIP": 0.343, "XBH": 91, "GIDP": 14, "GIDPO": 154, "NP": 5006, "P/PA": 3.74, "K/PA": 0.268, "HR/PA": 0.021, "BB/K": 0.265, "ISO": 0.133, "ROE": 0.133, "WO": 1.0, "FPCT %": 0.9470000000000001, "Pitches": 4795, "Batted Balls": 824, "Barrels": 31, "Barrel %": 3.8, "Exit Velocity": 84.2, "Launch Angle": 4.7, "XBA": 0.247, "XSLG": 0.363, "WOBA": 0.306, "XWOBA": 0.296, "XWOBACON": 0.373, "Hard Hit %": 31.5, "K %": 27.1, "BB %": 7.3, "Days injured": 96, "Number of injuries": 5, "Zone %": 48.4, "Zone Swing %": 66, "Zone Contact %": 82.3, "Chase %": 30.9, "Chase Contact %": 52.9, "Edge %": 43.2, "1st Pitch Swing %": 36.2, "Swing %": 48, "Whiff %": 27.5, "Meatball %": 7.3, "Meatball Swing %": 74.5, "% Rank": 92.4}], "Hernan Perez": [["Hernan Perez", "2B", "B/T: R/R", "6' 1\" 215", "Age: 28", "Villa de Cura,  Venezuela", "Player Apps", "Pitch Highlighter", "Player Similarity", "Shifts", "Zone Swing Profile", ["P", "1B", "2B", "3B", "SS", "LF", "CF", "RF", "OF"], "Vet"], {"Seasons": 8, "G": 629, "PA": 1799, "AB": 1701, "R": 190, "H": 432, "2B": 74, "3B": 11, "HR": 44, "RBI": 179, "BB": 74, "SO": 380, "SB": 69, "CS": 16, "HBP": 1.0, "AVG": 0.254, "OBP": 0.284, "SLG": 0.388, "OPS": 0.672, "TB": 660, "LOB": 756, "SAC": 11, "SF": 12, "BABIP": 0.301, "XBH": 129, "GIDP": 36, "GIDPO": 273, "NP": 6383, "P/PA": 3.55, "K/PA": 0.211, "HR/PA": 0.024, "BB/K": 0.195, "ISO": 0.134, "ROE": 0.134, "WO": 0.0, "FPCT %": 0.983, "Pitches": 6116, "Batted Balls": 1284, "Barrels": 45, "Barrel %": 3.5, "Exit Velocity": 86.5, "Launch Angle": 10.6, "XBA": 0.246, "XSLG": 0.365, "WOBA": 0.291, "XWOBA": 0.279, "XWOBACON": 0.337, "Hard Hit %": 32.4, "K %": 21.2, "BB %": 4.1, "Days injured": 0, "Number of injuries": 0, "Zone %": 50.1, "Zone Swing %": 66.8, "Zone Contact %": 82.3, "Chase %": 38.7, "Chase Contact %": 63.5, "Edge %": 41.5, "1st Pitch Swing %": 32.3, "Swing %": 52.8, "Whiff %": 24.6, "Meatball %": 7.3, "Meatball Swing %": 72.9, "% Rank": 56.9}], "Manny Pina": [["Manny Pina", "C", "B/T: R/R", "6' 0\" 215", "Age: 32", "Barquisimeto,  Venezuela", "Player Apps", "Pitch Highlighter", "Player Similarity", "Shifts", "Zone Swing Profile", ["C", "1B", "3B"], "Young guy"], {"Seasons": 6, "G": 314, "PA": 958, "AB": 871, "R": 100, "H": 224, "2B": 47, "3B": 2, "HR": 27, "RBI": 105, "BB": 65, "SO": 204, "SB": 4, "CS": 1.0, "HBP": 13, "AVG": 0.257, "OBP": 0.316, "SLG": 0.409, "OPS": 0.725, "TB": 356, "LOB": 389, "SAC": 2, "SF": 7, "BABIP": 0.304, "XBH": 76, "GIDP": 25, "GIDPO": 130, "NP": 3812, "P/PA": 3.98, "K/PA": 0.213, "HR/PA": 0.028, "BB/K": 0.319, "ISO": 0.152, "ROE": 0.152, "WO": 0.0, "Pitches": 3752, "Batted Balls": 662, "Barrels": 34, "Barrel %": 5.1, "Exit Velocity": 86.4, "Launch Angle": 16, "XBA": 0.246, "XSLG": 0.4, "WOBA": 0.313, "XWOBA": 0.308, "XWOBACON": 0.36, "Hard Hit %": 29.5, "K %": 21.5, "BB %": 6.8, "Days injured": 58, "Number of injuries": 7, "Zone %": 49.9, "Zone Swing %": 65.2, "Zone Contact %": 83.8, "Chase %": 28.8, "Chase Contact %": 63, "Edge %": 43.4, "1st Pitch Swing %": 21.5, "Swing %": 47, "Whiff %": 22.5, "Meatball %": 8, "Meatball Swing %": 73.3, "% Rank": 21.3}], "Jesus Aguilar": [["Jesus Aguilar", "1B", "B/T: R/R", "6' 3\" 250", "Age: 29", "Maracay,  Venezuela", "Player Apps", "Pitch Highlighter", "Player Similarity", "Shifts", "Zone Swing Profile", ["1B", "3B"], "Young guy"], {"Seasons": 6, "G": 436, "PA": 1286, "AB": 1123, "R": 159, "H": 288, "2B": 53, "3B": 2, "HR": 61, "RBI": 208, "BB": 128, "SO": 332, "SB": 0.0, "CS": 0.0, "HBP": 13, "AVG": 0.256, "OBP": 0.334, "SLG": 0.47, "OPS": 0.805, "TB": 528, "LOB": 515, "SAC": 0.0, "SF": 19, "BABIP": 0.303, "XBH": 116, "GIDP": 39, "GIDPO": 179, "NP": 5438, "P/PA": 4.23, "K/PA": 0.258, "HR/PA": 0.047, "BB/K": 0.386, "ISO": 0.214, "ROE": 0.214, "WO": 2, "Pitches": 5271, "Batted Balls": 789, "Barrels": 79, "Barrel %": 10, "Exit Velocity": 89.3, "Launch Angle": 14.2, "XBA": 0.25, "XSLG": 0.47, "WOBA": 0.348, "XWOBA": 0.346, "XWOBACON": 0.428, "Hard Hit %": 41, "K %": 25.6, "BB %": 9.9, "Days injured": 0, "Number of injuries": 0, "Zone %": 46, "Zone Swing %": 62.5, "Zone Contact %": 78.1, "Chase %": 31.1, "Chase Contact %": 58.6, "Edge %": 42, "1st Pitch Swing %": 15.5, "Swing %": 45.6, "Whiff %": 29.1, "Meatball %": 6.3, "Meatball Swing %": 68.4, "% Rank": 5.6}], "Orlando Arcia": [["Orlando Arcia", "SS", "B/T: R/R", "6' 0\" 165", "Age: 25", "Anaco,  Venezuela", "Player Apps", "Pitch Highlighter", "Player Similarity", "Shifts", "Zone Swing Profile", [], "Young guy"], {"Seasons": 4, "G": 462, "PA": 1619, "AB": 1495, "R": 156, "H": 362, "2B": 55, "3B": 6, "HR": 36, "RBI": 150, "BB": 108, "SO": 331, "SB": 37, "CS": 15, "HBP": 2, "AVG": 0.242, "OBP": 0.292, "SLG": 0.359, "OPS": 0.651, "TB": 537, "LOB": 618, "SAC": 4, "SF": 10, "BABIP": 0.286, "XBH": 97, "GIDP": 40, "GIDPO": 228, "NP": 6008, "P/PA": 3.71, "K/PA": 0.204, "HR/PA": 0.022, "BB/K": 0.326, "ISO": 0.117, "ROE": 0.117, "WO": 2, "FPCT %": 0.972, "Pitches": 6008, "Batted Balls": 1178, "Barrels": 44, "Barrel %": 3.7, "Exit Velocity": 86.2, "Launch Angle": 5.6, "XBA": 0.23, "XSLG": 0.335, "WOBA": 0.28, "XWOBA": 0.272, "XWOBACON": 0.314, "Hard Hit %": 29, "K %": 20.4, "BB %": 6.7, "Days injured": 0, "Number of injuries": 0, "Zone %": 49.7, "Zone Swing %": 69.5, "Zone Contact %": 80.1, "Chase %": 32.9, "Chase Contact %": 60, "Edge %": 42.3, "1st Pitch Swing %": 34.4, "Swing %": 51, "Whiff %": 26.4, "Meatball %": 7.8, "Meatball Swing %": 76.1, "% Rank": 41.1}], "Travis Shaw": [["Travis Shaw", "3B", "B/T: L/R", "6' 4\" 230", "Age: 29", "Draft: 2011 (Rd: 9, #292, Boston Red Sox )  - Kent State", "Washington Court House, OH USA", "Player Apps", "Pitch Highlighter", "Player Similarity", "Shifts", "Zone Swing Profile", ["1B", "2B", "3B", "LF", "OF"], "Young guy"], {"Seasons": 5, "G": 579, "PA": 2224, "AB": 1960, "R": 269, "H": 477, "2B": 106, "3B": 3, "HR": 98, "RBI": 308, "BB": 230, "SO": 518, "SB": 20, "CS": 4, "HBP": 17, "AVG": 0.243, "OBP": 0.326, "SLG": 0.451, "OPS": 0.776, "TB": 883, "LOB": 918, "SAC": 2, "SF": 15, "BABIP": 0.279, "XBH": 207, "GIDP": 43, "GIDPO": 267, "NP": 9035, "P/PA": 4.06, "K/PA": 0.233, "HR/PA": 0.044, "BB/K": 0.444, "ISO": 0.207, "ROE": 0.207, "WO": 2, "FPCT %": 0.9640000000000001, "Pitches": 9035, "Batted Balls": 1459, "Barrels": 120, "Barrel %": 8.2, "Exit Velocity": 88.4, "Launch Angle": 16.4, "XBA": 0.237, "XSLG": 0.427, "WOBA": 0.331, "XWOBA": 0.324, "XWOBACON": 0.381, "Hard Hit %": 37.1, "K %": 23.3, "BB %": 10.3, "Days injured": 10, "Number of injuries": 1, "Zone %": 46, "Zone Swing %": 66.3, "Zone Contact %": 83.4, "Chase %": 28, "Chase Contact %": 64.5, "Edge %": 43.6, "1st Pitch Swing %": 24.7, "Swing %": 45.6, "Whiff %": 22.9, "Meatball %": 6.4, "Meatball Swing %": 75.3, "% Rank": 23.3}], "Tyler Saladino": [["Tyler Saladino", "SS", "B/T: R/R", "6' 0\" 200", "Age: 30", "Draft: 2010 (Rd: 7, #218, Chicago White Sox )  - Oral Roberts", "San Diego, CA USA", "Player Apps", "Pitch Highlighter", "Player Similarity", "Shifts", "Zone Swing Profile", ["1B", "2B", "3B", "SS", "LF", "CF", "RF", "OF"], "Young guy"], {"Seasons": 5, "G": 326, "PA": 1064, "AB": 978, "R": 109, "H": 221, "2B": 33, "3B": 6, "HR": 19, "RBI": 92, "BB": 62, "SO": 247, "SB": 28, "CS": 13, "HBP": 10, "AVG": 0.226, "OBP": 0.278, "SLG": 0.33, "OPS": 0.608, "TB": 323, "LOB": 445, "SAC": 9, "SF": 5, "BABIP": 0.282, "XBH": 58, "GIDP": 29, "GIDPO": 148, "NP": 4166, "P/PA": 3.92, "K/PA": 0.232, "HR/PA": 0.018, "BB/K": 0.251, "ISO": 0.104, "ROE": 0.104, "WO": 3, "FPCT %": 0.9670000000000001, "Pitches": 4166, "Batted Balls": 745, "Barrels": 20, "Barrel %": 2.7, "Exit Velocity": 85.7, "Launch Angle": 9.4, "XBA": 0.237, "XSLG": 0.334, "WOBA": 0.268, "XWOBA": 0.277, "XWOBACON": 0.329, "Hard Hit %": 30.7, "K %": 23.2, "BB %": 5.8, "Days injured": 63, "Number of injuries": 7, "Zone %": 52.8, "Zone Swing %": 62.2, "Zone Contact %": 84.5, "Chase %": 24.3, "Chase Contact %": 59.6, "Edge %": 43.5, "1st Pitch Swing %": 20.7, "Swing %": 44.3, "Whiff %": 22, "Meatball %": 8, "Meatball Swing %": 74.3, "% Rank": 73.5}], "Mauricio Dubon": [["Mauricio Dubon", "SS", "B/T: R/R", "6' 0\" 160", "Age: 25", "Draft: 2013 (Rd: 26, #773, Boston Red Sox )  - Capital Christian (CA) HS", "San Pedro Sula,  Honduras", "MLB Pipeline Rank:", "SF", ": No. 8", "Player Apps", "Pitch Highlighter", "Player Similarity", "Shifts", "Zone Swing Profile", ["2B", "SS"], "Rookie"], {"Seasons": 1, "G": 14, "PA": 44, "AB": 42, "R": 4, "H": 12, "2B": 3, "3B": 0.0, "HR": 2, "RBI": 5, "BB": 2, "SO": 4, "SB": 2, "CS": 0.0, "HBP": 0.0, "AVG": 0.286, "OBP": 0.318, "SLG": 0.5, "OPS": 0.818, "TB": 21, "LOB": 17, "SAC": 0.0, "SF": 0.0, "BABIP": 0.278, "XBH": 5, "GIDP": 1.0, "GIDPO": 8, "NP": 166, "P/PA": 3.77, "K/PA": 0.091, "HR/PA": 0.045, "BB/K": 0.5, "ISO": 0.214, "ROE": 0.214, "WO": 0.0, "FPCT %": 1.0, "Pitches": 166, "Batted Balls": 38, "Barrels": 1.0, "Barrel %": 2.6, "Exit Velocity": 83.8, "Launch Angle": 13.1, "XBA": 0.237, "XSLG": 0.369, "WOBA": 0.345, "XWOBA": 0.282, "XWOBACON": 0.291, "Hard Hit %": 21.1, "K %": 9.1, "BB %": 4.5, "Days injured": 0, "Number of injuries": 0, "Zone %": 45.5, "Zone Swing %": 77.3, "Zone Contact %": 86.2, "Chase %": 42.2, "Chase Contact %": 84.2, "Edge %": 35.2, "1st Pitch Swing %": 31.8, "Swing %": 58.4, "Whiff %": 14.4, "Meatball %": 6.7, "Meatball Swing %": 63.6, "% Rank": 59.4}], "David Freitas": [["David Freitas", "C", "B/T: R/R", "6' 3\" 225", "Age: 30", "Draft: 2010 (Rd: 15, #446, Washington Nationals )  - Hawaii", "Wilton, CA USA", "Player Apps", "Pitch Highlighter", "Player Similarity", "Shifts", "Zone Swing Profile", ["C", "1B"], "Young guy"], {"Seasons": 3, "G": 53, "PA": 137, "AB": 119, "R": 13, "H": 24, "2B": 8, "3B": 0.0, "HR": 1.0, "RBI": 8, "BB": 12, "SO": 31, "SB": 0.0, "CS": 0.0, "HBP": 0.0, "AVG": 0.202, "OBP": 0.273, "SLG": 0.294, "OPS": 0.567, "TB": 35, "LOB": 46, "SAC": 1.0, "SF": 1.0, "BABIP": 0.261, "XBH": 9, "GIDP": 4, "GIDPO": 19, "NP": 544, "P/PA": 3.97, "K/PA": 0.226, "HR/PA": 0.007, "BB/K": 0.387, "ISO": 0.092, "ROE": 0.092, "WO": 0.0, "Pitches": 544, "Batted Balls": 90, "Barrels": 4, "Barrel %": 4.4, "Exit Velocity": 88.7, "Launch Angle": 7.7, "XBA": 0.231, "XSLG": 0.365, "WOBA": 0.253, "XWOBA": 0.296, "XWOBACON": 0.345, "Hard Hit %": 33.7, "K %": 22.6, "BB %": 8.8, "Days injured": 7, "Number of injuries": 1, "Zone %": 49.8, "Zone Swing %": 74.8, "Zone Contact %": 83.7, "Chase %": 22.8, "Chase Contact %": 61.3, "Edge %": 43.7, "1st Pitch Swing %": 37.2, "Swing %": 48.9, "Whiff %": 21.4, "Meatball %": 7.4, "Meatball Swing %": 82.5, "% Rank": 11.6}]}, "Pitchers": {"Junior Guerra": [["Junior Guerra", "P", "B/T: R/R", "6' 0\" 205", "Age: 34", "San Felix,  Venezuela", "Player Apps", "Pitch Highlighter", "Visual Pitch Report", "Player Similarity", "3d Pitches", "Pitch Mix", "Plinko", "Texture Map", "Shifts", "Zone Swing Profile", [], "Young guy"], {"Hitting AB": 89, "Hitting HR": 0, "Hitting BB": 0, "Hitting SO": 32, "AVG": 0.146, "Seasons": 5, "BF": 1753, "W": 25, "L": 21, "ERA": 3.84, "G": 141, "GS": 60, "SV": 3, "IP": 414.1, "H": 356, "R": 195, "ER": 177, "HR": 59, "BB": 177, "SO": 380, "WHIP": 1.29, "FPCT %": 0.932, "Pitches": 6785, "Batted Balls": 1180, "Barrels": 81, "Barrel %": 6.9, "Exit Velocity": 87.2, "Launch Angle": 13.1, "XBA": 0.241, "XSLG": 0.402, "WOBA": 0.311, "XWOBA": 0.319, "XWOBACON": 0.362, "Hard Hit %": 34.3, "K %": 21.7, "BB %": 10.1, "Days injured": 45, "Number of injuries": 4, "Zone %": 46.5, "Zone Swing %": 68.7, "Zone Contact %": 81.9, "Chase %": 26.4, "Chase Contact %": 57.7, "Edge %": 40.8, "1st Pitch Swing %": 30.4, "Swing %": 46.1, "Whiff %": 25.6, "Meatball %": 6.3, "Meatball Swing %": 78, "% Rank": 9.2}], "Aaron Wilkerson": [["Aaron Wilkerson", "P", "B/T: R/R", "6' 3\" 190", "Age: 30", "Fort Worth, TX USA", "Player Apps", "Pitch Highlighter", "Visual Pitch Report", "Player Similarity", "3d Pitches", "Pitch Mix", "Plinko", "Texture Map", "Shifts", "Zone Swing Profile", [], "Young guy"], {"Hitting AB": 9, "Hitting HR": 1, "Hitting BB": 0, "Hitting SO": 3, "AVG": 0.111, "Seasons": 3, "BF": 160, "W": 1.0, "L": 1.0, "ERA": 6.88, "G": 14, "GS": 3, "SV": 0.0, "IP": 35.1, "H": 43, "R": 27, "ER": 27, "HR": 9, "BB": 13, "SO": 28, "WHIP": 1.58, "FPCT %": 1.0, "Pitches": 637, "Batted Balls": 118, "Barrels": 5, "Barrel %": 4.2, "Exit Velocity": 85.2, "Launch Angle": 15.9, "XBA": 0.249, "XSLG": 0.406, "WOBA": 0.378, "XWOBA": 0.31, "XWOBACON": 0.342, "Hard Hit %": 27.1, "K %": 17.5, "BB %": 8.1, "Days injured": 24, "Number of injuries": 3, "Zone %": 45.8, "Zone Swing %": 64.9, "Zone Contact %": 83.1, "Chase %": 25.8, "Chase Contact %": 69.7, "Edge %": 44.5, "1st Pitch Swing %": 26.3, "Swing %": 43.8, "Whiff %": 21.5, "Meatball %": 7.4, "Meatball Swing %": 76.6}], "Corbin Burnes": [["Corbin Burnes", "P", "B/T: R/R", "6' 3\" 205", "Age: 24", "Draft: 2016 (Rd: 4, #111, Milwaukee Brewers )  - St. Mary's", "Bakersfield, CA USA", "Player Apps", "Pitch Highlighter", "Visual Pitch Report", "Player Similarity", "3d Pitches", "Pitch Mix", "Plinko", "Texture Map", "Shifts", "Zone Swing Profile", [], "Young guy"], {"Hitting AB": 7, "Hitting HR": 0, "Hitting BB": 0, "Hitting SO": 2, "AVG": 0.286, "Seasons": 2, "BF": 375, "W": 8, "L": 5, "ERA": 6.11, "G": 60, "GS": 4, "SV": 2, "IP": 84, "H": 93, "R": 61, "ER": 57, "HR": 20, "BB": 31, "SO": 102, "WHIP": 1.48, "FPCT %": 0.85, "Pitches": 1440, "Batted Balls": 239, "Barrels": 24, "Barrel %": 10, "Exit Velocity": 88.6, "Launch Angle": 9.2, "XBA": 0.261, "XSLG": 0.456, "WOBA": 0.358, "XWOBA": 0.338, "XWOBACON": 0.436, "Hard Hit %": 36.7, "K %": 27.2, "BB %": 8.3, "Days injured": 0, "Number of injuries": 0, "Zone %": 49.4, "Zone Swing %": 67.9, "Zone Contact %": 78.8, "Chase %": 31.1, "Chase Contact %": 35.7, "Edge %": 39.8, "1st Pitch Swing %": 29.1, "Swing %": 49.2, "Whiff %": 35.1, "Meatball %": 7.1, "Meatball Swing %": 83.2}], "Brandon Woodruff": [["Brandon Woodruff", "P", "B/T: L/R", "6' 4\" 215", "Age: 26", "Draft: 2014 (Rd: 11, #326, Milwaukee Brewers )  - Mississippi State", "Tupelo, MS USA", "Player Apps", "Pitch Highlighter", "Visual Pitch Report", "Player Similarity", "3d Pitches", "Pitch Mix", "Plinko", "Texture Map", "Shifts", "Zone Swing Profile", [], "Young guy"], {"Hitting AB": 63, "Hitting HR": 1, "Hitting BB": 3, "Hitting SO": 23, "AVG": 0.254, "Seasons": 3, "BF": 840, "W": 16, "L": 6, "ERA": 3.95, "G": 47, "GS": 32, "SV": 1.0, "IP": 203, "H": 188, "R": 90, "ER": 89, "HR": 21, "BB": 57, "SO": 215, "WHIP": 1.21, "FPCT %": 0.973, "Pitches": 3370, "Batted Balls": 558, "Barrels": 25, "Barrel %": 4.5, "Exit Velocity": 85.4, "Launch Angle": 10.3, "XBA": 0.24, "XSLG": 0.369, "WOBA": 0.293, "XWOBA": 0.296, "XWOBACON": 0.362, "Hard Hit %": 31, "K %": 25.6, "BB %": 6.8, "Days injured": 10, "Number of injuries": 1, "Zone %": 50.7, "Zone Swing %": 69.9, "Zone Contact %": 81.9, "Chase %": 28.8, "Chase Contact %": 60.6, "Edge %": 44.8, "1st Pitch Swing %": 31.2, "Swing %": 49.6, "Whiff %": 24.3, "Meatball %": 7.4, "Meatball Swing %": 76.8, "% Rank": 9.0}], "Zach Davies": [["Zach Davies", "P", "B/T: R/R", "6' 0\" 155", "Age: 26", "Draft: 2011 (Rd: 26, #785, Baltimore Orioles )  - Mesquite (AZ) HS", "Puyallup, WA USA", "Player Apps", "Pitch Highlighter", "Visual Pitch Report", "Player Similarity", "3d Pitches", "Pitch Mix", "Plinko", "Texture Map", "Shifts", "Zone Swing Profile", [], "Young guy"], {"Hitting AB": 177, "Hitting HR": 0, "Hitting BB": 9, "Hitting SO": 71, "AVG": 0.113, "Seasons": 5, "BF": 2537, "W": 42, "L": 32, "ERA": 3.97, "G": 108, "GS": 108, "SV": 0.0, "IP": 600.1, "H": 611, "R": 289, "ER": 265, "HR": 70, "BB": 177, "SO": 426, "WHIP": 1.31, "FPCT %": 0.955, "Pitches": 9823, "Batted Balls": 1911, "Barrels": 97, "Barrel %": 5.1, "Exit Velocity": 86.5, "Launch Angle": 9.1, "XBA": 0.271, "XSLG": 0.418, "WOBA": 0.319, "XWOBA": 0.326, "XWOBACON": 0.362, "Hard Hit %": 31.8, "K %": 16.8, "BB %": 7, "Days injured": 44, "Number of injuries": 5, "Zone %": 44.2, "Zone Swing %": 63.5, "Zone Contact %": 86.2, "Chase %": 27.3, "Chase Contact %": 71, "Edge %": 45.7, "1st Pitch Swing %": 23.5, "Swing %": 43.3, "Whiff %": 19.1, "Meatball %": 5.3, "Meatball Swing %": 74.5, "% Rank": 13.5}], "Freddy Peralta": [["Freddy Peralta", "P", "B/T: R/R", "5' 11\" 175", "Age: 23", "Moca,  Dominican Republic", "Player Apps", "Pitch Highlighter", "Visual Pitch Report", "Player Similarity", "3d Pitches", "Pitch Mix", "Plinko", "Texture Map", "Shifts", "Zone Swing Profile", [], "Young guy"], {"Hitting AB": 40, "Hitting HR": 0, "Hitting BB": 0, "Hitting SO": 19, "AVG": 0.075, "Seasons": 2, "BF": 680, "W": 11, "L": 7, "ERA": 4.99, "G": 50, "GS": 22, "SV": 1.0, "IP": 157, "H": 134, "R": 92, "ER": 87, "HR": 23, "BB": 76, "SO": 199, "WHIP": 1.34, "FPCT %": 1.0, "Pitches": 2875, "Batted Balls": 399, "Barrels": 35, "Barrel %": 8.8, "Exit Velocity": 88.5, "Launch Angle": 18.8, "XBA": 0.216, "XSLG": 0.386, "WOBA": 0.317, "XWOBA": 0.307, "XWOBACON": 0.384, "Hard Hit %": 38.3, "K %": 29.3, "BB %": 11.2, "Days injured": 10, "Number of injuries": 1, "Zone %": 50.2, "Zone Swing %": 66.9, "Zone Contact %": 78.8, "Chase %": 26.8, "Chase Contact %": 56.5, "Edge %": 43.9, "1st Pitch Swing %": 26.9, "Swing %": 47, "Whiff %": 27.6, "Meatball %": 8.3, "Meatball Swing %": 73.6, "% Rank": 4.6}], "Jhoulys Chacin": [["Jhoulys Chacin", "P", "B/T: R/R", "6' 3\" 215", "Age: 31", "Maracaibo,  Venezuela", "Player Apps", "Pitch Highlighter", "Visual Pitch Report", "Player Similarity", "3d Pitches", "Pitch Mix", "Plinko", "Texture Map", "Shifts", "Zone Swing Profile", [], "Vet"], {"Hitting AB": 355, "Hitting HR": 2, "Hitting BB": 11, "Hitting SO": 86, "AVG": 0.183, "Seasons": 11, "BF": 5577, "W": 77, "L": 85, "ERA": 3.99, "G": 251, "GS": 222, "SV": 0.0, "IP": 1307.1, "H": 1205, "R": 630, "ER": 579, "HR": 134, "BB": 528, "SO": 1047, "WHIP": 1.33, "FPCT %": 0.955, "Pitches": 10468, "Batted Balls": 1901, "Barrels": 114, "Barrel %": 6, "Exit Velocity": 87.2, "Launch Angle": 10.5, "XBA": 0.259, "XSLG": 0.413, "WOBA": 0.311, "XWOBA": 0.328, "XWOBACON": 0.368, "Hard Hit %": 35.5, "K %": 19.6, "BB %": 9.1, "Days injured": 125, "Number of injuries": 6, "Zone %": 48.9, "Zone Swing %": 61.7, "Zone Contact %": 87.2, "Chase %": 24.7, "Chase Contact %": 60.7, "Edge %": 43.1, "1st Pitch Swing %": 24.7, "Swing %": 42.7, "Whiff %": 20.6, "Meatball %": 7.2, "Meatball Swing %": 72.7, "% Rank": 8.6}], "Jordan Lyles": [["Jordan Lyles", "P", "B/T: R/R", "6' 5\" 230", "Age: 28", "Draft: 2008 (Rd: CA, #38, Houston Astros )  - Hartsville HS", "Hartsville, SC USA", "Popularity:", "\u2191 14%", "Player Apps", "Pitch Highlighter", "Visual Pitch Report", "Player Similarity", "3d Pitches", "Pitch Mix", "Plinko", "Texture Map", "Shifts", "Zone Swing Profile", [], "Vet"], {"Hitting AB": 210, "Hitting HR": 2, "Hitting BB": 11, "Hitting SO": 105, "AVG": 0.114, "Seasons": 9, "BF": 3945, "W": 41, "L": 60, "ERA": 5.15, "G": 242, "GS": 140, "SV": 2, "IP": 894, "H": 979, "R": 568, "ER": 512, "HR": 119, "BB": 310, "SO": 677, "WHIP": 1.44, "FPCT %": 0.943, "Pitches": 6578, "Batted Balls": 1223, "Barrels": 70, "Barrel %": 5.7, "Exit Velocity": 87.6, "Launch Angle": 9.7, "XBA": 0.254, "XSLG": 0.41, "WOBA": 0.34, "XWOBA": 0.321, "XWOBACON": 0.361, "Hard Hit %": 36.4, "K %": 19.1, "BB %": 8.6, "Days injured": 150, "Number of injuries": 5, "Zone %": 48.4, "Zone Swing %": 67.7, "Zone Contact %": 86.4, "Chase %": 27.5, "Chase Contact %": 59.8, "Edge %": 42.7, "1st Pitch Swing %": 31.7, "Swing %": 46.9, "Whiff %": 21.6, "Meatball %": 7, "Meatball Swing %": 74.1, "% Rank": 1.8}], "Chase Anderson": [["Chase Anderson", "P", "B/T: R/R", "6' 1\" 200", "Age: 31", "Draft: 2009 (Rd: 9, #276, Arizona Diamondbacks )  - Oklahoma", "Wichita Falls, TX USA", "Player Apps", "Pitch Highlighter", "Visual Pitch Report", "Player Similarity", "3d Pitches", "Pitch Mix", "Plinko", "Texture Map", "Shifts", "Zone Swing Profile", [], "Young guy"], {"Hitting AB": 259, "Hitting HR": 0, "Hitting BB": 4, "Hitting SO": 137, "AVG": 0.089, "Seasons": 6, "BF": 3519, "W": 51, "L": 40, "ERA": 3.99, "G": 163, "GS": 157, "SV": 0.0, "IP": 842, "H": 791, "R": 397, "ER": 373, "HR": 127, "BB": 276, "SO": 709, "WHIP": 1.27, "FPCT %": 0.9520000000000001, "Pitches": 12107, "Batted Balls": 2160, "Barrels": 148, "Barrel %": 6.9, "Exit Velocity": 86.3, "Launch Angle": 15.1, "XBA": 0.251, "XSLG": 0.418, "WOBA": 0.321, "XWOBA": 0.321, "XWOBACON": 0.366, "Hard Hit %": 30, "K %": 19.9, "BB %": 7.8, "Days injured": 80, "Number of injuries": 9, "Zone %": 48.5, "Zone Swing %": 67.8, "Zone Contact %": 82.4, "Chase %": 26.9, "Chase Contact %": 67.5, "Edge %": 43.1, "1st Pitch Swing %": 30.1, "Swing %": 46.7, "Whiff %": 22, "Meatball %": 7, "Meatball Swing %": 78.1, "% Rank": 7.5}], "Adrian Houser": [["Adrian Houser", "P", "B/T: R/R", "6' 4\" 235", "Age: 26", "Draft: 2011 (Rd: 2, #69, Houston Astros )  - Locust Grove (OK) HS", "Tahlequah, OK USA", "Player Apps", "Pitch Highlighter", "Visual Pitch Report", "Player Similarity", "3d Pitches", "Pitch Mix", "Plinko", "Texture Map", "Shifts", "Zone Swing Profile", [], "Young guy"], {"Hitting AB": 20, "Hitting HR": 0, "Hitting BB": 1, "Hitting SO": 15, "AVG": 0.05, "Seasons": 3, "BF": 467, "W": 6, "L": 5, "ERA": 3.49, "G": 40, "GS": 14, "SV": 0.0, "IP": 111, "H": 104, "R": 46, "ER": 43, "HR": 12, "BB": 42, "SO": 107, "WHIP": 1.32, "FPCT %": 0.9440000000000001, "Pitches": 1804, "Batted Balls": 312, "Barrels": 14, "Barrel %": 4.5, "Exit Velocity": 86.6, "Launch Angle": 5.4, "XBA": 0.227, "XSLG": 0.347, "WOBA": 0.314, "XWOBA": 0.29, "XWOBACON": 0.33, "Hard Hit %": 34.9, "K %": 22.9, "BB %": 9, "Days injured": 14, "Number of injuries": 2, "Zone %": 48.3, "Zone Swing %": 65.1, "Zone Contact %": 82, "Chase %": 25.3, "Chase Contact %": 60.2, "Edge %": 44.8, "1st Pitch Swing %": 26.6, "Swing %": 44.6, "Whiff %": 24.4, "Meatball %": 7, "Meatball Swing %": 77.8}], "Gio Gonzalez": [["Gio Gonzalez", "P", "B/T: R/L", "6' 0\" 205", "Age: 33", "Draft: 2004 (Rd: C1, #38, Chicago White Sox )  - Monsignor Edward Pace HS (FL)", "Hialeah, FL USA", "Popularity:", "\u2191 80%", "Player Apps", "Pitch Highlighter", "Visual Pitch Report", "Player Similarity", "3d Pitches", "Pitch Mix", "Plinko", "Texture Map", "Shifts", "Zone Swing Profile", [], "Vet"], {"Hitting AB": 405, "Hitting HR": 3, "Hitting BB": 9, "Hitting SO": 188, "AVG": 0.089, "Seasons": 12, "BF": 8027, "W": 129, "L": 99, "ERA": 3.7, "G": 328, "GS": 322, "SV": 0.0, "IP": 1886.1, "H": 1690, "R": 836, "ER": 776, "HR": 165, "BB": 793, "SO": 1811, "WHIP": 1.32, "FPCT %": 0.97, "Pitches": 13711, "Batted Balls": 2318, "Barrels": 129, "Barrel %": 5.6, "Exit Velocity": 86.7, "Launch Angle": 8.7, "XBA": 0.25, "XSLG": 0.395, "WOBA": 0.308, "XWOBA": 0.316, "XWOBACON": 0.364, "Hard Hit %": 32.6, "K %": 21.7, "BB %": 9.4, "Days injured": 35, "Number of injuries": 3, "Zone %": 44.5, "Zone Swing %": 63.8, "Zone Contact %": 83, "Chase %": 26.3, "Chase Contact %": 63.7, "Edge %": 43.2, "1st Pitch Swing %": 24.3, "Swing %": 43.1, "Whiff %": 23.6, "Meatball %": 5.5, "Meatball Swing %": 71.5, "% Rank": NaN}], "Josh Hader": [["Josh Hader", "P", "B/T: L/L", "6' 3\" 185", "Age: 25", "Draft: 2012 (Rd: 19, #582, Baltimore Orioles )  - Old Mill Senior HS (MD)", "Millersville, MD USA", "Player Apps", "Pitch Highlighter", "Visual Pitch Report", "Player Similarity", "3d Pitches", "Pitch Mix", "Plinko", "Texture Map", "Shifts", "Zone Swing Profile", [], "Young guy"], {"Hitting AB": 8, "Hitting HR": 0, "Hitting BB": 0, "Hitting SO": 4, "AVG": 0.125, "Seasons": 3, "BF": 749, "W": 11, "L": 9, "ERA": 2.39, "G": 143, "GS": 0.0, "SV": 42, "IP": 196, "H": 96, "R": 55, "ER": 52, "HR": 26, "BB": 70, "SO": 335, "WHIP": 0.85, "FPCT %": 1.0, "Pitches": 3148, "Batted Balls": 336, "Barrels": 33, "Barrel %": 9.8, "Exit Velocity": 87.1, "Launch Angle": 22.2, "XBA": 0.158, "XSLG": 0.29, "WOBA": 0.236, "XWOBA": 0.241, "XWOBACON": 0.379, "Hard Hit %": 33.3, "K %": 44.7, "BB %": 9.3, "Days injured": 0, "Number of injuries": 0, "Zone %": 52.4, "Zone Swing %": 74.1, "Zone Contact %": 64.2, "Chase %": 30.5, "Chase Contact %": 48.7, "Edge %": 44.2, "1st Pitch Swing %": 37.4, "Swing %": 53.4, "Whiff %": 40.1, "Meatball %": 7.7, "Meatball Swing %": 85.9}], "Donnie Hart": [["Donnie Hart", "P", "B/T: L/L", "5' 11\" 180", "Age: 29", "Draft: 2013 (Rd: 27, #819, Baltimore Orioles )  - Texas State", "Bedford, TX USA", "Player Apps", "Pitch Highlighter", "Visual Pitch Report", "Player Similarity", "3d Pitches", "Pitch Mix", "Plinko", "Texture Map", "Shifts", "Zone Swing Profile", [], "Young guy"], {"Hitting AB": 3, "Hitting HR": 0, "Hitting BB": 0, "Hitting SO": 2, "AVG": 0.0, "Seasons": 4, "BF": 389, "W": 2, "L": 0.0, "ERA": 3.13, "G": 98, "GS": 0.0, "SV": 0.0, "IP": 89, "H": 95, "R": 33, "ER": 31, "HR": 8, "BB": 35, "SO": 57, "WHIP": 1.46, "FPCT %": 0.9570000000000001, "Pitches": 1466, "Batted Balls": 293, "Barrels": 14, "Barrel %": 4.8, "Exit Velocity": 85.6, "Launch Angle": 7.2, "XBA": 0.249, "XSLG": 0.381, "WOBA": 0.32, "XWOBA": 0.312, "XWOBACON": 0.324, "Hard Hit %": 29.8, "K %": 14.7, "BB %": 9, "Days injured": 0, "Number of injuries": 0, "Zone %": 44.9, "Zone Swing %": 64.5, "Zone Contact %": 84.4, "Chase %": 28.2, "Chase Contact %": 62.6, "Edge %": 39.2, "1st Pitch Swing %": 25.4, "Swing %": 44.5, "Whiff %": 23.2, "Meatball %": 7.6, "Meatball Swing %": 70.3}], "Jay Jackson": [["Jay Jackson", "P", "B/T: R/R", "6' 1\" 195", "Age: 31", "Draft: 2008 (Rd: 9, #281, Chicago Cubs )  - Furman", "Greenville, SC USA", "Player Apps", "Pitch Highlighter", "Visual Pitch Report", "Player Similarity", "3d Pitches", "Pitch Mix", "Plinko", "Texture Map", "Shifts", "Zone Swing Profile", [], "Young guy"], {"Hitting AB": 2, "Hitting HR": 0, "Hitting BB": 0, "Hitting SO": 2, "AVG": 0.0, "Seasons": 2, "BF": 130, "W": 1.0, "L": 0.0, "ERA": 5.22, "G": 28, "GS": 0.0, "SV": 0.0, "IP": 29.1, "H": 28, "R": 17, "ER": 17, "HR": 5, "BB": 14, "SO": 41, "WHIP": 1.43, "FPCT %": 1.0, "Pitches": 535, "Batted Balls": 73, "Barrels": 9, "Barrel %": 12.3, "Exit Velocity": 89.4, "Launch Angle": 15, "XBA": 0.26, "XSLG": 0.48, "WOBA": 0.334, "XWOBA": 0.355, "XWOBACON": 0.487, "Hard Hit %": 39.7, "K %": 31.5, "BB %": 10.8, "Days injured": 21, "Number of injuries": 3, "Zone %": 42.6, "Zone Swing %": 69.3, "Zone Contact %": 77.2, "Chase %": 31.9, "Chase Contact %": 43.9, "Edge %": 43.6, "1st Pitch Swing %": 32.3, "Swing %": 47.9, "Whiff %": 35.5, "Meatball %": 5.4, "Meatball Swing %": 75.9}], "Jeremy Jeffress": [["Jeremy Jeffress", "P", "B/T: R/R", "6' 0\" 205", "Age: 31", "Draft: 2006 (Rd: 1, #16, Milwaukee Brewers )  - Halifax County Sr HS", "South Boston, VA USA", "Player Apps", "Pitch Highlighter", "Visual Pitch Report", "Player Similarity", "3d Pitches", "Pitch Mix", "Plinko", "Texture Map", "Shifts", "Zone Swing Profile", [], "Vet"], {"Hitting AB": 3, "Hitting HR": 0, "Hitting BB": 0, "Hitting SO": 3, "AVG": 0.0, "Seasons": 10, "BF": 1705, "W": 28, "L": 11, "ERA": 3.16, "G": 392, "GS": 1.0, "SV": 44, "IP": 401, "H": 377, "R": 155, "ER": 141, "HR": 30, "BB": 163, "SO": 370, "WHIP": 1.35, "FPCT %": 0.953, "Pitches": 5165, "Batted Balls": 917, "Barrels": 37, "Barrel %": 4, "Exit Velocity": 85.6, "Launch Angle": 2.2, "XBA": 0.249, "XSLG": 0.367, "WOBA": 0.296, "XWOBA": 0.303, "XWOBACON": 0.351, "Hard Hit %": 31.4, "K %": 21.9, "BB %": 8.8, "Days injured": 44, "Number of injuries": 5, "Zone %": 48.9, "Zone Swing %": 63.9, "Zone Contact %": 83.3, "Chase %": 29.8, "Chase Contact %": 56.7, "Edge %": 44.6, "1st Pitch Swing %": 25.4, "Swing %": 46.5, "Whiff %": 25.3, "Meatball %": 7.2, "Meatball Swing %": 67}], "Jimmy Nelson": [["Jimmy Nelson", "P", "B/T: R/R", "6' 6\" 250", "Age: 30", "Draft: 2010 (Rd: 2, #64, Milwaukee Brewers )  - Alabama", "Klamath Falls, OR USA", "Player Apps", "Pitch Highlighter", "Visual Pitch Report", "Player Similarity", "3d Pitches", "Pitch Mix", "Plinko", "Texture Map", "Shifts", "Zone Swing Profile", [], "Young guy"], {"Hitting AB": 188, "Hitting HR": 0, "Hitting BB": 4, "Hitting SO": 113, "AVG": 0.101, "Seasons": 6, "BF": 2720, "W": 33, "L": 46, "ERA": 4.23, "G": 115, "GS": 107, "SV": 0.0, "IP": 627.2, "H": 627, "R": 331, "ER": 295, "HR": 68, "BB": 238, "SO": 569, "WHIP": 1.38, "FPCT %": 0.9079999999999999, "Pitches": 8847, "Batted Balls": 1613, "Barrels": 80, "Barrel %": 5, "Exit Velocity": 86.4, "Launch Angle": 6.9, "XBA": 0.247, "XSLG": 0.382, "WOBA": 0.324, "XWOBA": 0.315, "XWOBACON": 0.356, "Hard Hit %": 31.8, "K %": 21.2, "BB %": 9, "Days injured": 207, "Number of injuries": 6, "Zone %": 51.2, "Zone Swing %": 63.3, "Zone Contact %": 84.3, "Chase %": 27.9, "Chase Contact %": 61.6, "Edge %": 43.2, "1st Pitch Swing %": 27.7, "Swing %": 46, "Whiff %": 22.4, "Meatball %": 8.2, "Meatball Swing %": 69.9, "% Rank": 9.6}], "Drew Pomeranz": [["Drew Pomeranz", "P", "B/T: R/L", "6' 6\" 240", "Age: 30", "Draft: 2010 (Rd: 1, #5, Cleveland Indians )  - Ole Miss", "Collierville, TN USA", "Popularity:", "\u2193 -50%", "Player Apps", "Pitch Highlighter", "Visual Pitch Report", "Player Similarity", "3d Pitches", "Pitch Mix", "Plinko", "Texture Map", "Shifts", "Zone Swing Profile", [], "Vet"], {"Hitting AB": 89, "Hitting HR": 2, "Hitting BB": 1, "Hitting SO": 54, "AVG": 0.135, "Seasons": 9, "BF": 3464, "W": 46, "L": 58, "ERA": 4.07, "G": 234, "GS": 140, "SV": 4, "IP": 805.1, "H": 755, "R": 393, "ER": 364, "HR": 106, "BB": 349, "SO": 806, "WHIP": 1.37, "FPCT %": 0.924, "Pitches": 10633, "Batted Balls": 1674, "Barrels": 125, "Barrel %": 7.5, "Exit Velocity": 87.6, "Launch Angle": 12, "XBA": 0.242, "XSLG": 0.401, "WOBA": 0.318, "XWOBA": 0.317, "XWOBACON": 0.378, "Hard Hit %": 34.8, "K %": 24.4, "BB %": 9.8, "Days injured": 77, "Number of injuries": 7, "Zone %": 48.2, "Zone Swing %": 64, "Zone Contact %": 82.5, "Chase %": 27.4, "Chase Contact %": 61.4, "Edge %": 42.3, "1st Pitch Swing %": 25, "Swing %": 45.1, "Whiff %": 24.2, "Meatball %": 7.5, "Meatball Swing %": 71.2}], "Burch Smith": [["Burch Smith", "P", "B/T: R/R", "6' 4\" 225", "Age: 29", "Draft: 2011 (Rd: 14, #443, San Diego Padres )  - Oklahoma", "San Antonio, TX USA", "Player Apps", "Pitch Highlighter", "Visual Pitch Report", "Player Similarity", "3d Pitches", "Pitch Mix", "Plinko", "Texture Map", "Shifts", "Zone Swing Profile", [], "Young guy"], {"Hitting AB": 10, "Hitting HR": 0, "Hitting BB": 1, "Hitting SO": 3, "AVG": 0.1, "Seasons": 3, "BF": 600, "W": 2, "L": 10, "ERA": 6.73, "G": 58, "GS": 13, "SV": 0.0, "IP": 129.2, "H": 146, "R": 97, "ER": 97, "HR": 27, "BB": 71, "SO": 138, "WHIP": 1.67, "FPCT %": 0.938, "Pitches": 1733, "Batted Balls": 286, "Barrels": 25, "Barrel %": 8.7, "Exit Velocity": 88.8, "Launch Angle": 14.5, "XBA": 0.252, "XSLG": 0.453, "WOBA": 0.371, "XWOBA": 0.348, "XWOBACON": 0.398, "Hard Hit %": 40.9, "K %": 21.2, "BB %": 11.5, "Days injured": 88, "Number of injuries": 5, "Zone %": 49.5, "Zone Swing %": 68.5, "Zone Contact %": 80.2, "Chase %": 25.5, "Chase Contact %": 62.8, "Edge %": 43.2, "1st Pitch Swing %": 26.8, "Swing %": 46.7, "Whiff %": 24.6, "Meatball %": 8.5, "Meatball Swing %": 79.6}], "Devin Williams": [["Devin Williams", "P", "B/T: R/R", "6' 3\" 165", "Age: 24", "Draft: 2013 (Rd: 2, #54, Milwaukee Brewers )  - Hazelwood West (MO) HS", "Florissant, MO USA", "MLB Pipeline Rank:", "MIL", ": No. 14", "Player Apps", "Pitch Highlighter", "Visual Pitch Report", "Player Similarity", "3d Pitches", "Pitch Mix", "Plinko", "Texture Map", "Shifts", "Zone Swing Profile", [], "Rookie"], {"Hitting AB": 1, "Hitting HR": 0, "Hitting BB": 0, "Hitting SO": 1, "AVG": 0.0, "Seasons": 1, "BF": 48, "W": 0.0, "L": 0.0, "ERA": 4, "G": 8, "GS": 0.0, "SV": 0.0, "IP": 9, "H": 14, "R": 7, "ER": 4, "HR": 1.0, "BB": 5, "SO": 8, "WHIP": 2.11, "FPCT %": NaN, "Pitches": 188, "Batted Balls": 33, "Barrels": 3, "Barrel %": 9.1, "Exit Velocity": 85.3, "Launch Angle": 9.5, "XBA": 0.246, "XSLG": 0.421, "WOBA": 0.403, "XWOBA": 0.345, "XWOBACON": 0.354, "Hard Hit %": 27.3, "K %": 16.7, "BB %": 10.4, "Days injured": 7, "Number of injuries": 1, "Zone %": 47.9, "Zone Swing %": 75.6, "Zone Contact %": 73.5, "Chase %": 24.5, "Chase Contact %": 70.8, "Edge %": 35.6, "1st Pitch Swing %": 39.6, "Swing %": 48.9, "Whiff %": 27.2, "Meatball %": 8, "Meatball Swing %": 93.3}], "Taylor Williams": [["Taylor Williams", "P", "B/T: S/R", "5' 11\" 195", "Age: 28", "Draft: 2013 (Rd: 4, #122, Milwaukee Brewers )  - Kent State", "Vancouver, WA USA", "Player Apps", "Pitch Highlighter", "Visual Pitch Report", "Player Similarity", "3d Pitches", "Pitch Mix", "Plinko", "Texture Map", "Shifts", "Zone Swing Profile", [], "Young guy"], {"Hitting AB": 5, "Hitting HR": 0, "Hitting BB": 0, "Hitting SO": 4, "AVG": 0.2, "Seasons": 3, "BF": 316, "W": 2, "L": 4, "ERA": 5.45, "G": 69, "GS": 0.0, "SV": 0.0, "IP": 69.1, "H": 77, "R": 45, "ER": 42, "HR": 7, "BB": 32, "SO": 72, "WHIP": 1.57, "FPCT %": 1.0, "Pitches": 1235, "Batted Balls": 209, "Barrels": 12, "Barrel %": 5.7, "Exit Velocity": 87.6, "Launch Angle": 9.8, "XBA": 0.272, "XSLG": 0.4, "WOBA": 0.335, "XWOBA": 0.326, "XWOBACON": 0.387, "Hard Hit %": 39.2, "K %": 22.8, "BB %": 10.1, "Days injured": 77, "Number of injuries": 3, "Zone %": 46.7, "Zone Swing %": 68.1, "Zone Contact %": 77.9, "Chase %": 26.9, "Chase Contact %": 50.3, "Edge %": 41.4, "1st Pitch Swing %": 30.7, "Swing %": 46.2, "Whiff %": 30.7, "Meatball %": 6.8, "Meatball Swing %": 84.5}], "Matt Albers": [["Matt Albers", "P", "B/T: L/R", "6' 1\" 225", "Age: 36", "Draft: 2001 (Rd: 23, #686, Houston Astros )  - Clements School HS (Sugar Land, TX)", "Houston, TX USA", "Popularity:", "\u2193 -14%", "Player Apps", "Pitch Highlighter", "Visual Pitch Report", "Player Similarity", "3d Pitches", "Pitch Mix", "Plinko", "Texture Map", "Shifts", "Zone Swing Profile", [], "Old timer"], {"Hitting AB": 35, "Hitting HR": 0, "Hitting BB": 0, "Hitting SO": 21, "AVG": 0.086, "Seasons": 14, "BF": 3279, "W": 45, "L": 47, "ERA": 4.34, "G": 612, "GS": 24, "SV": 7, "IP": 757, "H": 747, "R": 397, "ER": 365, "HR": 85, "BB": 314, "SO": 569, "WHIP": 1.4, "FPCT %": 0.946, "Pitches": 4059, "Batted Balls": 717, "Barrels": 47, "Barrel %": 6.6, "Exit Velocity": 85.8, "Launch Angle": 7.5, "XBA": 0.247, "XSLG": 0.402, "WOBA": 0.316, "XWOBA": 0.315, "XWOBACON": 0.358, "Hard Hit %": 30.7, "K %": 20.3, "BB %": 8.4, "Days injured": 110, "Number of injuries": 5, "Zone %": 44.8, "Zone Swing %": 64.1, "Zone Contact %": 85.9, "Chase %": 27.7, "Chase Contact %": 64.7, "Edge %": 42.2, "1st Pitch Swing %": 25.6, "Swing %": 44, "Whiff %": 21.4, "Meatball %": 6.8, "Meatball Swing %": 76.8}], "Jacob Barnes": [["Jacob Barnes", "P", "B/T: R/R", "6' 2\" 220", "Age: 29", "Draft: 2011 (Rd: 14, #431, Milwaukee Brewers )  - Florida Gulf Coast", "St. Petersburg, FL USA", "Player Apps", "Pitch Highlighter", "Visual Pitch Report", "Player Similarity", "3d Pitches", "Pitch Mix", "Plinko", "Texture Map", "Shifts", "Zone Swing Profile", [], "Young guy"], {"Hitting AB": 0, "Hitting HR": 0, "Hitting BB": 1, "Hitting SO": 0, "AVG": 0, "Seasons": 4, "BF": 759, "W": 4, "L": 8, "ERA": 4.12, "G": 175, "GS": 1.0, "SV": 5, "IP": 174.2, "H": 163, "R": 93, "ER": 80, "HR": 19, "BB": 78, "SO": 179, "WHIP": 1.38, "FPCT %": 0.833, "Pitches": 3009, "Batted Balls": 499, "Barrels": 27, "Barrel %": 5.4, "Exit Velocity": 86.5, "Launch Angle": 6.8, "XBA": 0.23, "XSLG": 0.358, "WOBA": 0.304, "XWOBA": 0.296, "XWOBACON": 0.344, "Hard Hit %": 31.7, "K %": 23.6, "BB %": 10.3, "Days injured": 43, "Number of injuries": 5, "Zone %": 44.8, "Zone Swing %": 70.7, "Zone Contact %": 79.3, "Chase %": 28.9, "Chase Contact %": 49, "Edge %": 42.1, "1st Pitch Swing %": 33.5, "Swing %": 47.7, "Whiff %": 30.8, "Meatball %": 6.3, "Meatball Swing %": 81.1}], "Ray Black": [["Ray Black", "P", "B/T: R/R", "6' 5\" 225", "Age: 29", "Draft: 2011 (Rd: 7, #237, San Francisco Giants )  - Pittsburgh", "Wilkes-Barre, PA USA", "Player Apps", "Pitch Highlighter", "Visual Pitch Report", "Player Similarity", "3d Pitches", "Pitch Mix", "Plinko", "Texture Map", "Shifts", "Zone Swing Profile", [], "Young guy"], {"Hitting AB": 0, "Hitting HR": 0, "Hitting BB": 0, "Hitting SO": 0, "AVG": 0, "Seasons": 2, "BF": 139, "W": 2, "L": 2, "ERA": 4.93, "G": 37, "GS": 0.0, "SV": 0.0, "IP": 34.2, "H": 24, "R": 19, "ER": 19, "HR": 6, "BB": 14, "SO": 44, "WHIP": 1.1, "FPCT %": 1.0, "Pitches": 596, "Batted Balls": 79, "Barrels": 5, "Barrel %": 6.3, "Exit Velocity": 85.1, "Launch Angle": 19.2, "XBA": 0.202, "XSLG": 0.35, "WOBA": 0.306, "XWOBA": 0.288, "XWOBACON": 0.369, "Hard Hit %": 35.4, "K %": 31.7, "BB %": 10.1, "Days injured": 155, "Number of injuries": 7, "Zone %": 48.1, "Zone Swing %": 67.7, "Zone Contact %": 73.1, "Chase %": 26.7, "Chase Contact %": 50, "Edge %": 38.3, "1st Pitch Swing %": 28.8, "Swing %": 46.6, "Whiff %": 33.8, "Meatball %": 8.8, "Meatball Swing %": 88.5}], "Alex Claudio": [["Alex Claudio", "P", "B/T: L/L", "6' 3\" 180", "Age: 27", "Draft: 2010 (Rd: 27, #826, Texas Rangers )  - Isabel Flores HS", "San Juan,  Puerto Rico", "Player Apps", "Pitch Highlighter", "Visual Pitch Report", "Player Similarity", "3d Pitches", "Pitch Mix", "Plinko", "Texture Map", "Shifts", "Zone Swing Profile", [], "Young guy"], {"Hitting AB": 0, "Hitting HR": 0, "Hitting BB": 0, "Hitting SO": 0, "AVG": 0, "Seasons": 6, "BF": 1210, "W": 15, "L": 8, "ERA": 3.33, "G": 285, "GS": 2, "SV": 12, "IP": 289, "H": 297, "R": 116, "ER": 107, "HR": 23, "BB": 70, "SO": 201, "WHIP": 1.27, "FPCT %": 1.0, "Pitches": 4166, "Batted Balls": 889, "Barrels": 28, "Barrel %": 3.1, "Exit Velocity": 85.7, "Launch Angle": 1.3, "XBA": 0.255, "XSLG": 0.36, "WOBA": 0.304, "XWOBA": 0.293, "XWOBACON": 0.324, "Hard Hit %": 31.4, "K %": 16.2, "BB %": 5.7, "Days injured": 84, "Number of injuries": 4, "Zone %": 48.1, "Zone Swing %": 63.6, "Zone Contact %": 84.6, "Chase %": 33.4, "Chase Contact %": 62, "Edge %": 43, "1st Pitch Swing %": 27.5, "Swing %": 47.9, "Whiff %": 23.6, "Meatball %": 6.3, "Meatball Swing %": 66.3}], "Jake Faria": [["Jake Faria", "P", "B/T: R/R", "6' 4\" 225", "Age: 26", "Draft: 2011 (Rd: 10, #330, Tampa Bay Rays )  - Gahr (CA) HS", "La Palma, CA USA", "Player Apps", "Pitch Highlighter", "Visual Pitch Report", "Player Similarity", "3d Pitches", "Pitch Mix", "Plinko", "Texture Map", "Shifts", "Zone Swing Profile", [], "Young guy"], {"Hitting AB": 0, "Hitting HR": 0, "Hitting BB": 0, "Hitting SO": 0, "AVG": 0, "Seasons": 3, "BF": 709, "W": 9, "L": 8, "ERA": 4.26, "G": 45, "GS": 26, "SV": 0.0, "IP": 167, "H": 149, "R": 81, "ER": 79, "HR": 24, "BB": 72, "SO": 149, "WHIP": 1.32, "FPCT %": 0.9570000000000001, "Pitches": 2879, "Batted Balls": 480, "Barrels": 37, "Barrel %": 7.7, "Exit Velocity": 88.4, "Launch Angle": 17.1, "XBA": 0.249, "XSLG": 0.425, "WOBA": 0.32, "XWOBA": 0.334, "XWOBACON": 0.378, "Hard Hit %": 37.9, "K %": 21, "BB %": 10.2, "Days injured": 70, "Number of injuries": 2, "Zone %": 48, "Zone Swing %": 67.3, "Zone Contact %": 82.1, "Chase %": 25.4, "Chase Contact %": 55.8, "Edge %": 40.4, "1st Pitch Swing %": 28.9, "Swing %": 45.5, "Whiff %": 25.6, "Meatball %": 7.7, "Meatball Swing %": 82}], "Deolis Guerra": [["Deolis Guerra", "P", "B/T: R/R", "6' 5\" 245", "Age: 30", "San Felix,  Venezuela", "Player Apps", "Pitch Highlighter", "Visual Pitch Report", "Player Similarity", "3d Pitches", "Pitch Mix", "Plinko", "Texture Map", "Shifts", "Zone Swing Profile", [], "Young guy"], {"Hitting AB": 1, "Hitting HR": 0, "Hitting BB": 0, "Hitting SO": 0, "AVG": 0.0, "Seasons": 4, "BF": 405, "W": 7, "L": 2, "ERA": 4.52, "G": 74, "GS": 0.0, "SV": 0.0, "IP": 95.2, "H": 102, "R": 52, "ER": 48, "HR": 16, "BB": 22, "SO": 75, "WHIP": 1.3, "FPCT %": 1.0, "Pitches": 1649, "Batted Balls": 305, "Barrels": 21, "Barrel %": 6.9, "Exit Velocity": 87.1, "Launch Angle": 14.9, "XBA": 0.262, "XSLG": 0.445, "WOBA": 0.333, "XWOBA": 0.325, "XWOBACON": 0.375, "Hard Hit %": 32.1, "K %": 18.5, "BB %": 5.4, "Days injured": 88, "Number of injuries": 5, "Zone %": 44.9, "Zone Swing %": 68.6, "Zone Contact %": 84.1, "Chase %": 31.9, "Chase Contact %": 59.2, "Edge %": 41.8, "1st Pitch Swing %": 29.6, "Swing %": 48.4, "Whiff %": 24.9, "Meatball %": 7, "Meatball Swing %": 87.1}], "Jake Petricka": [["Jake Petricka", "P", "B/T: R/R", "6' 5\" 220", "Age: 31", "Draft: 2010 (Rd: 2, #63, Chicago White Sox )  - Indiana State", "Northfield, MN USA", "Player Apps", "Pitch Highlighter", "Visual Pitch Report", "Player Similarity", "3d Pitches", "Pitch Mix", "Plinko", "Texture Map", "Shifts", "Zone Swing Profile", [], "Vet"], {"Hitting AB": 1, "Hitting HR": 0, "Hitting BB": 0, "Hitting SO": 1, "AVG": 0.0, "Seasons": 7, "BF": 1017, "W": 10, "L": 12, "ERA": 3.96, "G": 228, "GS": 0.0, "SV": 16, "IP": 231.2, "H": 255, "R": 109, "ER": 102, "HR": 18, "BB": 97, "SO": 175, "WHIP": 1.52, "FPCT %": 1.0, "Pitches": 2335, "Batted Balls": 454, "Barrels": 19, "Barrel %": 4.2, "Exit Velocity": 87.8, "Launch Angle": 3.1, "XBA": 0.27, "XSLG": 0.39, "WOBA": 0.356, "XWOBA": 0.321, "XWOBACON": 0.354, "Hard Hit %": 34.6, "K %": 17.6, "BB %": 8.6, "Days injured": 129, "Number of injuries": 8, "Zone %": 48.5, "Zone Swing %": 65.1, "Zone Contact %": 86.7, "Chase %": 27, "Chase Contact %": 57.7, "Edge %": 42.7, "1st Pitch Swing %": 27, "Swing %": 45.4, "Whiff %": 22.1, "Meatball %": 7.2, "Meatball Swing %": 78.1}], "Brent Suter": [["Brent Suter", "P", "B/T: L/L", "6' 5\" 195", "Age: 30", "Draft: 2012 (Rd: 31, #965, Milwaukee Brewers )  - Harvard", "Chicago, IL USA", "Player Apps", "Pitch Highlighter", "Visual Pitch Report", "Player Similarity", "3d Pitches", "Pitch Mix", "Plinko", "Texture Map", "Shifts", "Zone Swing Profile", [], "Young guy"], {"Hitting AB": 46, "Hitting HR": 1, "Hitting BB": 4, "Hitting SO": 15, "AVG": 0.174, "Seasons": 4, "BF": 889, "W": 15, "L": 11, "ERA": 3.79, "G": 60, "GS": 34, "SV": 0.0, "IP": 214, "H": 215, "R": 97, "ER": 90, "HR": 30, "BB": 46, "SO": 170, "WHIP": 1.22, "FPCT %": 0.941, "Pitches": 3389, "Batted Balls": 666, "Barrels": 38, "Barrel %": 5.7, "Exit Velocity": 83.7, "Launch Angle": 12.3, "XBA": 0.257, "XSLG": 0.404, "WOBA": 0.31, "XWOBA": 0.306, "XWOBACON": 0.356, "Hard Hit %": 24.6, "K %": 19.1, "BB %": 5.2, "Days injured": 140, "Number of injuries": 4, "Zone %": 51.1, "Zone Swing %": 65.2, "Zone Contact %": 84, "Chase %": 30, "Chase Contact %": 62.9, "Edge %": 43.5, "1st Pitch Swing %": 26.5, "Swing %": 47.9, "Whiff %": 22.4, "Meatball %": 7.6, "Meatball Swing %": 68.9, "% Rank": 49.5}], "Alex Wilson": [["Alex Wilson", "P", "B/T: R/R", "6' 0\" 220", "Age: 32", "Draft: 2009 (Rd: 2, #77, Boston Red Sox )  - Texas A&M", "Dhahran,  Saudi Arabia", "Player Apps", "Pitch Highlighter", "Visual Pitch Report", "Player Similarity", "3d Pitches", "Pitch Mix", "Plinko", "Texture Map", "Shifts", "Zone Swing Profile", [], "Vet"], {"Hitting AB": 0, "Hitting HR": 0, "Hitting BB": 0, "Hitting SO": 0, "AVG": 0, "Seasons": 7, "BF": 1368, "W": 14, "L": 14, "ERA": 3.44, "G": 303, "GS": 1.0, "SV": 5, "IP": 332, "H": 315, "R": 139, "ER": 127, "HR": 31, "BB": 90, "SO": 226, "WHIP": 1.22, "FPCT %": 0.9590000000000001, "Pitches": 4238, "Batted Balls": 868, "Barrels": 54, "Barrel %": 6.2, "Exit Velocity": 87.2, "Launch Angle": 11.1, "XBA": 0.254, "XSLG": 0.408, "WOBA": 0.294, "XWOBA": 0.308, "XWOBACON": 0.346, "Hard Hit %": 32.9, "K %": 16.3, "BB %": 6.3, "Days injured": 92, "Number of injuries": 4, "Zone %": 45.8, "Zone Swing %": 69.1, "Zone Contact %": 89.6, "Chase %": 31.7, "Chase Contact %": 65.1, "Edge %": 44.3, "1st Pitch Swing %": 30.6, "Swing %": 48.8, "Whiff %": 19.1, "Meatball %": 5.7, "Meatball Swing %": 78.4}]}}